antigate/__init__.py
antigate-1.3.4.dist-info/DESCRIPTION.rst
antigate-1.3.4.dist-info/METADATA
antigate-1.3.4.dist-info/metadata.json
antigate-1.3.4.dist-info/RECORD
antigate-1.3.4.dist-info/top_level.txt
antigate-1.3.4.dist-info/WHEEL
